{"ancestors":["Thing","Action","TradeAction"],"comment":"","comment_plain":"","id":"SellAction","label":"Sell Action","properties":{"additionalType":"URL","alternateName":"Text","description":"Text","image":"URL","name":"Text","sameAs":"URL","url":"URL","agent":["Organization","Person"],"endTime":"DateTime","instrument":"Thing","location":["PostalAddress","Place"],"object":"Thing","participant":["Organization","Person"],"result":"Thing","startTime":"DateTime","price":["Text","Number"],"buyer":"Person","warrantyPromise":"WarrantyPromise"},"specific_properties":["buyer","warrantyPromise"],"subtypes":[],"supertypes":["TradeAction"],"url":"http://schema.org/SellAction"}